em/__init__.py
em/emojis.json
em_keyboard_py3-0.0.7.2.dist-info/DESCRIPTION.rst
em_keyboard_py3-0.0.7.2.dist-info/METADATA
em_keyboard_py3-0.0.7.2.dist-info/RECORD
em_keyboard_py3-0.0.7.2.dist-info/WHEEL
em_keyboard_py3-0.0.7.2.dist-info/entry_points.txt
em_keyboard_py3-0.0.7.2.dist-info/metadata.json
em_keyboard_py3-0.0.7.2.dist-info/top_level.txt
