Metadata-Version: 2.0
Name: em-keyboard-py3
Version: 0.0.7.2
Summary: The CLI Emoji Keyboard
Home-page: https://github.com/c17r/em-keyboard-py3
Author: Christian Sauer
Author-email: sauerc@gmail.com
License: ISC
Platform: UNKNOWN
Classifier: Intended Audience :: Developers
Classifier: Natural Language :: English
Classifier: License :: OSI Approved :: ISC License (ISCL)
Classifier: Programming Language :: Python
Classifier: Programming Language :: Python :: 2.6
Classifier: Programming Language :: Python :: 2.7
Classifier: Programming Language :: Python :: 3
Classifier: Programming Language :: Python :: 3.3
Classifier: Programming Language :: Python :: 3.4
Classifier: Programming Language :: Python :: 3.5
Classifier: Programming Language :: Python :: 3.6
Classifier: Programming Language :: Python :: Implementation :: CPython
Requires-Dist: docopt
Requires-Dist: xerox
